jsw_wcc/fonts/qnhghp.ttf
jsw_wcc/main.py
jsw_wcc-0.1.11.dist-info/entry_points.txt
jsw_wcc-0.1.11.dist-info/WHEEL
jsw_wcc-0.1.11.dist-info/METADATA
jsw_wcc-0.1.11.dist-info/RECORD
