Metadata-Version: 2.1
Name: jsw-wcc
Version: 0.1.11
Summary: Add water mark for image based on python.
License: MIT
Author: afeiship
Author-email: 1290657123@qq.com
Requires-Python: >=3.10,<4.0
Classifier: License :: OSI Approved :: MIT License
Classifier: Programming Language :: Python :: 3
Classifier: Programming Language :: Python :: 3.10
Classifier: Programming Language :: Python :: 3.11
Requires-Dist: Pillow (>=9.3.0,<10.0.0)
